decyphr/.DS_Store
decyphr/__init__.py
decyphr/main_orchestrator.py
decyphr/analysis_plugins/.DS_Store
decyphr/analysis_plugins/__init__.py
decyphr/analysis_plugins/p01_overview/.DS_Store
decyphr/analysis_plugins/p01_overview/__init__.py
decyphr/analysis_plugins/p01_overview/create_visualization.py
decyphr/analysis_plugins/p01_overview/run_analysis.py
decyphr/analysis_plugins/p02_univariate/.DS_Store
decyphr/analysis_plugins/p02_univariate/__init__.py
decyphr/analysis_plugins/p02_univariate/create_visualization.py
decyphr/analysis_plugins/p02_univariate/run_analysis.py
decyphr/analysis_plugins/p03_data_quality/.DS_Store
decyphr/analysis_plugins/p03_data_quality/__init__.py
decyphr/analysis_plugins/p03_data_quality/create_visualization.py
decyphr/analysis_plugins/p03_data_quality/run_analysis.py
decyphr/analysis_plugins/p04_advanced_outliers/.DS_Store
decyphr/analysis_plugins/p04_advanced_outliers/__init__.py
decyphr/analysis_plugins/p04_advanced_outliers/create_visualization.py
decyphr/analysis_plugins/p04_advanced_outliers/run_analysis.py
decyphr/analysis_plugins/p05_missing_values/.DS_Store
decyphr/analysis_plugins/p05_missing_values/__init__.py
decyphr/analysis_plugins/p05_missing_values/create_visualization.py
decyphr/analysis_plugins/p05_missing_values/run_analysis.py
decyphr/analysis_plugins/p06_correlations/.DS_Store
decyphr/analysis_plugins/p06_correlations/__init__.py
decyphr/analysis_plugins/p06_correlations/create_visualization.py
decyphr/analysis_plugins/p06_correlations/run_analysis.py
decyphr/analysis_plugins/p07_interactions/.DS_Store
decyphr/analysis_plugins/p07_interactions/__init__.py
decyphr/analysis_plugins/p07_interactions/create_visualization.py
decyphr/analysis_plugins/p07_interactions/run_analysis.py
decyphr/analysis_plugins/p08_hypothesis_testing/.DS_Store
decyphr/analysis_plugins/p08_hypothesis_testing/__init__.py
decyphr/analysis_plugins/p08_hypothesis_testing/create_visualization.py
decyphr-1.1.2.dist-info/licenses/LICENSE
decyphr-1.1.2.dist-info/METADATA
decyphr-1.1.2.dist-info/WHEEL
decyphr-1.1.2.dist-info/top_level.txt
decyphr-1.1.2.dist-info/RECORD
