Metadata-Version: 2.4
Name: decyphr
Version: 1.1.2
Summary: An all-encompassing, automated toolkit for deep Exploratory Data Analysis and reporting.
Author-email: Ayush Singh <emailtoayushsingh@gmail.com>
License: MIT License
Project-URL: Homepage, https://github.com/ayushagain/decyphr_project
Project-URL: Bug Tracker, https://github.com/ayushagain/decyphr_project/issues
Project-URL: Documentation, https://github.com/ayushagain/decyphr_project#readme
Keywords: eda,data analysis,profiling,visualization,data science,machine learning
Classifier: Development Status :: 3 - Alpha
Classifier: Programming Language :: Python :: 3
Classifier: Programming Language :: Python :: 3.9
Classifier: Programming Language :: Python :: 3.10
Classifier: Programming Language :: Python :: 3.11
Classifier: License :: OSI Approved :: MIT License
Classifier: Operating System :: OS Independent
Classifier: Intended Audience :: Developers
Classifier: Intended Audience :: Science/Research
Classifier: Topic :: Scientific/Engineering :: Information Analysis
Classifier: Topic :: Scientific/Engineering :: Visualization
Requires-Python: >=3.9
License-File: LICENSE
Requires-Dist: pandas>=2.0.0
Requires-Dist: dask[dataframe]>=2024.1.0
Requires-Dist: numpy>=1.24.0
Requires-Dist: openpyxl>=3.1.2
Requires-Dist: plotly>=5.15.0
Requires-Dist: jinja2>=3.1.0
Requires-Dist: scikit-learn>=1.3.0
Requires-Dist: scipy>=1.10.0
Requires-Dist: statsmodels>=0.14.0
Requires-Dist: phik>=0.12.4
Provides-Extra: text
Requires-Dist: spacy>=3.7.0; extra == "text"
Requires-Dist: textblob>=0.17.0; extra == "text"
Requires-Dist: gensim>=4.3.0; extra == "text"
Requires-Dist: wordcloud>=1.9.0; extra == "text"
Provides-Extra: xai
Requires-Dist: lightgbm>=4.0.0; extra == "xai"
Requires-Dist: shap>=0.42.0; extra == "xai"
Provides-Extra: geo
Requires-Dist: geopandas>=0.14.0; extra == "geo"
Requires-Dist: folium>=0.15.0; extra == "geo"
Requires-Dist: geohash2>=1.1; extra == "geo"
Provides-Extra: all
Requires-Dist: decyphr[text]; extra == "all"
Requires-Dist: decyphr[xai]; extra == "all"
Requires-Dist: decyphr[geo]; extra == "all"
Dynamic: license-file
